{
  "css/chat_box.css": "css/chat_box-1b33a0d501.css",
  "css/footer.css": "css/footer-eb88f01a70.css",
  "css/forgot-password.css": "css/forgot-password-4ba9e5926a.css",
  "css/header.css": "css/header-53a43bd32b.css",
  "css/home.css": "css/home-15305c79d9.css",
  "css/layout.css": "css/layout-0ed7895392.css",
  "css/posts.css": "css/posts-d41d8cd98f.css",
  "css/user_profile.css": "css/user_profile-2a06dee5f4.css",
  "css/user_signin.css": "css/user_signin-ba3af5b113.css",
  "css/user_signup.css": "css/user_signup-8b778d5719.css",
  "images/facebook.png": "images/facebook-d978d1b137.png",
  "images/header-background.png": "images/header-background-b0e594c69d.png",
  "js/chat_engine.js": "js/chat_engine-56e92d01dd.js",
  "js/home_posts.js": "js/home_posts-2ecc4f28f6.js",
  "js/home_posts_comments.js": "js/home_posts_comments-fd09c234fd.js",
  "js/toggle_likes.js": "js/toggle_likes-6888e2eea1.js"
}